MANIFEST.in
README.rst
setup.py
findagg/__init__.py
findagg/findagg.py
findagg/requirements.json
findagg/template.json
findagg.egg-info/PKG-INFO
findagg.egg-info/SOURCES.txt
findagg.egg-info/dependency_links.txt
findagg.egg-info/entry_points.txt
findagg.egg-info/requires.txt
findagg.egg-info/top_level.txt