Metadata-Version: 1.1
Name: findagg
Version: 0.6.1
Summary: CMIP5 aggregation discovery upon local TDS IPSL-ESGF datanode or CICLAD filesystem.
Home-page: http://prodiguer.github.io/find-agg/
Author: Levavasseur Guillaume
Author-email: glipsl@ipsl.jussieu.fr
License: UNKNOWN
Platform: UNKNOWN
Classifier: Development Status :: 5 - Production/Stable
Classifier: Environment :: Console
Classifier: Intended Audience :: Science/Research
Classifier: Intended Audience :: System Administrators
Classifier: Natural Language :: English
Classifier: Operating System :: Unix
Classifier: Programming Language :: Python :: 2.5
Classifier: Topic :: Scientific/Engineering
Classifier: Topic :: Software Development :: Build Tools
